connect4/__init__.py
connect4/__main__.py
connect4/controllers.py
connect4/py.typed
python_connect4-0.1.0.dist-info/METADATA
python_connect4-0.1.0.dist-info/WHEEL
python_connect4-0.1.0.dist-info/entry_points.txt
python_connect4-0.1.0.dist-info/RECORD
