Metadata-Version: 2.1
Name: python-connect4
Version: 0.1.0
Summary: Multiplayer implementation of "connect four" game
Home-page: https://nekeal.github.io/connect4
License: MIT
Author: Nekeal
Author-email: szymon.sc.cader@gmail.com
Requires-Python: >=3.9.1,<4.0
Classifier: Development Status :: 4 - Beta
Classifier: Intended Audience :: Developers
Classifier: License :: OSI Approved :: MIT License
Classifier: Operating System :: OS Independent
Classifier: Programming Language :: Python
Classifier: Programming Language :: Python :: 3
Classifier: Programming Language :: Python :: 3.10
Classifier: Programming Language :: Python :: 3.11
Classifier: Programming Language :: Python :: 3.8
Classifier: Programming Language :: Python :: 3.9
Classifier: Topic :: Software Development :: Libraries :: Python Modules
Classifier: Typing :: Typed
Requires-Dist: click
Project-URL: Documentation, https://nekeal.github.io/connect4
Project-URL: Repository, https://github.com/nekeal/connect4
